blew/__init__.py
blew-0.0.1.dist-info/METADATA
blew-0.0.1.dist-info/WHEEL
blew-0.0.1.dist-info/entry_points.txt
blew-0.0.1.dist-info/top_level.txt
blew-0.0.1.dist-info/RECORD
