Metadata-Version: 2.1
Name: blew
Version: 0.0.1
Summary: ai in development
Home-page: https://github.com/blew/blew
Author: blew
Author-email: blew.ai@gmail.com
License: MIT
Classifier: License :: OSI Approved :: MIT License
Classifier: Programming Language :: Python :: 3
Classifier: Programming Language :: Python :: 3.7
